arcade_collection/__init__.py
arcade_collection/__main__.py
arcade_collection/convert/__init__.py
arcade_collection/convert/convert_to_contours.py
arcade_collection/convert/convert_to_images.py
arcade_collection/convert/convert_to_meshes.py
arcade_collection/convert/convert_to_projection.py
arcade_collection/convert/convert_to_simularium.py
arcade_collection/convert/convert_to_simularium_objects.py
arcade_collection/convert/convert_to_simularium_shapes.py
arcade_collection/convert/convert_to_tfe.py
arcade_collection/input/__init__.py
arcade_collection/input/convert_to_cells_file.py
arcade_collection/input/convert_to_locations_file.py
arcade_collection/input/generate_setup_file.py
arcade_collection/input/group_template_conditions.py
arcade_collection/input/merge_region_samples.py
arcade_collection/output/__init__.py
arcade_collection/output/convert_model_units.py
arcade_collection/output/extract_tick_json.py
arcade_collection/output/get_location_voxels.py
arcade_collection/output/parse_cells_file.py
arcade_collection/output/parse_growth_file.py
arcade_collection/output/parse_locations_file.py
arcade_collection/py.typed
arcade_collection-0.16.0.dist-info/LICENSE
arcade_collection-0.16.0.dist-info/METADATA
arcade_collection-0.16.0.dist-info/WHEEL
arcade_collection-0.16.0.dist-info/RECORD
