Metadata-Version: 2.1
Name: arcade-collection
Version: 0.16.0
Summary: Collection of tasks for working with ARCADE.
License: BSD-3-Clause
Author: Jessica S. Yu
Author-email: jesyu@uw.edu
Requires-Python: >=3.9,<4.0
Classifier: License :: OSI Approved :: BSD License
Classifier: Programming Language :: Python :: 3
Classifier: Programming Language :: Python :: 3.9
Classifier: Programming Language :: Python :: 3.10
Classifier: Programming Language :: Python :: 3.11
Classifier: Programming Language :: Python :: 3.12
Requires-Dist: matplotlib (>=3.7.2,<4.0.0)
Requires-Dist: numpy (>=1.24.2,<2.0.0)
Requires-Dist: pandas (>=1.5.3,<2.0.0)
Requires-Dist: prefect (>=2.14.3,<3.0.0)
Requires-Dist: scikit-image (>=0.21.0,<0.22.0)
Requires-Dist: simulariumio (>=1.7.0,<2.0.0)
